AUTHORS.rst
CONTRIBUTING.rst
HISTORY.rst
LICENSE
MANIFEST.in
README.rst
setup.cfg
setup.py
django_simple_bugs.egg-info/PKG-INFO
django_simple_bugs.egg-info/SOURCES.txt
django_simple_bugs.egg-info/dependency_links.txt
django_simple_bugs.egg-info/not-zip-safe
django_simple_bugs.egg-info/requires.txt
django_simple_bugs.egg-info/top_level.txt
simple_bugs/__init__.py
simple_bugs/admin.py
simple_bugs/forms.py
simple_bugs/models.py
simple_bugs/search_indexes.py
simple_bugs/serializers.py
simple_bugs/tests.py
simple_bugs/urls.py
simple_bugs/views.py
simple_bugs/migrations/0001_initial.py
simple_bugs/migrations/0002_auto__add_case.py
simple_bugs/migrations/0003_auto__del_featurerequest__del_bug.py
simple_bugs/migrations/0004_auto__add_field_case_closed.py
simple_bugs/migrations/0005_auto__add_field_case_time_estimate.py
simple_bugs/migrations/0006_auto__add_field_case_assigned_to.py
simple_bugs/migrations/0007_auto.py
simple_bugs/migrations/0008_auto__add_historicalrequirement__add_historicalcase.py
simple_bugs/migrations/0009_auto__add_field_historicalcase_changed_by_id__add_field_case_changed_b.py
simple_bugs/migrations/0010_auto__add_field_requirement_changed_by__add_field_historicalrequiremen.py
simple_bugs/migrations/0011_auto__chg_field_requirement_changed_by.py
simple_bugs/migrations/0012_auto__chg_field_case_changed_by.py
simple_bugs/migrations/__init__.py
simple_bugs/static/ckeditor/build-config.js
simple_bugs/static/ckeditor/ckeditor.js
simple_bugs/static/ckeditor/config.js
simple_bugs/static/ckeditor/contents.css
simple_bugs/static/ckeditor/styles.js
simple_bugs/static/ckeditor/adapters/jquery.js
simple_bugs/static/ckeditor/lang/en.js
simple_bugs/static/ckeditor/plugins/icons.png
simple_bugs/static/ckeditor/plugins/icons_hidpi.png
simple_bugs/static/ckeditor/plugins/a11yhelp/dialogs/a11yhelp.js
simple_bugs/static/ckeditor/plugins/a11yhelp/dialogs/lang/ar.js
simple_bugs/static/ckeditor/plugins/a11yhelp/dialogs/lang/bg.js
simple_bugs/static/ckeditor/plugins/a11yhelp/dialogs/lang/ca.js
simple_bugs/static/ckeditor/plugins/a11yhelp/dialogs/lang/cs.js
simple_bugs/static/ckeditor/plugins/a11yhelp/dialogs/lang/cy.js
simple_bugs/static/ckeditor/plugins/a11yhelp/dialogs/lang/da.js
