Metadata-Version: 1.1
Name: django-simple-bugs
Version: 0.1.4
Summary: Bug tracking and project management app.
Home-page: https://github.com/thethc3/django_simple_bugs
Author: Thomas Cabral
Author-email: thethc3@gmail.com
License: MIT
Keywords: django_simple_bugs
Platform: UNKNOWN
Classifier: Development Status :: 2 - Pre-Alpha
Classifier: Framework :: Django
Classifier: Intended Audience :: Developers
Classifier: License :: OSI Approved :: BSD License
Classifier: Natural Language :: English
Classifier: Programming Language :: Python :: 2
Classifier: Programming Language :: Python :: 2.6
Classifier: Programming Language :: Python :: 2.7
Classifier: Programming Language :: Python :: 3
Classifier: Programming Language :: Python :: 3.3
